mub/__init__.py
mub/brainz.py
mub/main.py
mub/song.py
mub/util.py
mub-0.1.2.dist-info/LICENSE.txt
mub-0.1.2.dist-info/METADATA
mub-0.1.2.dist-info/WHEEL
mub-0.1.2.dist-info/entry_points.txt
mub-0.1.2.dist-info/RECORD
