Metadata-Version: 2.1
Name: mub
Version: 0.1.2
Summary: A cli app to download and cache album arts from mpd.
License: MIT
Author: Kutu
Author-email: the.kutu.dev@gmail.com
Requires-Python: >=3.11,<4.0
Classifier: License :: OSI Approved :: MIT License
Classifier: Programming Language :: Python :: 3
Classifier: Programming Language :: Python :: 3.11
Requires-Dist: musicbrainzngs (>=0.7.1,<0.8.0)
Requires-Dist: python-mpd2 (>=3.1.0,<4.0.0)
